django_key_auth-1.2.1.dist-info/DESCRIPTION.rst
django_key_auth-1.2.1.dist-info/METADATA
django_key_auth-1.2.1.dist-info/metadata.json
django_key_auth-1.2.1.dist-info/RECORD
django_key_auth-1.2.1.dist-info/top_level.txt
django_key_auth-1.2.1.dist-info/WHEEL
keyauth/__init__.py
keyauth/admin.py
keyauth/backends.py
keyauth/consts.py
keyauth/decorators.py
keyauth/exceptions.py
keyauth/managers.py
keyauth/middleware.py
keyauth/models.py
keyauth/utils.py
keyauth/migrations/0001_initial.py
keyauth/migrations/0002_auto_20150723_1538.py
keyauth/migrations/__init__.py
