Metadata-Version: 2.0
Name: django-key-auth
Version: 1.2.1
Summary: Key based authentication for Django
Home-page: https://github.com/laginha/django-key-auth
Author: Diogo Laginha
Author-email: diogo.laginha.machado@gmail.com
License: MIT
Platform: UNKNOWN
Classifier: License :: OSI Approved :: MIT License
Classifier: Programming Language :: Python :: 2
Classifier: Intended Audience :: Developers
Requires-Dist: django
Requires-Dist: rstr
Requires-Dist: django-mobileesp
